chartify/__init__.py
chartify/examples.py
chartify/_core/__init__.py
chartify/_core/axes.py
chartify/_core/callout.py
chartify/_core/chart.py
chartify/_core/colors.py
chartify/_core/colour.py
chartify/_core/options.py
chartify/_core/plot.py
chartify/_core/radar_chart.py
chartify/_core/style.py
chartify-5.0.1.dist-info/AUTHORS.rst
chartify-5.0.1.dist-info/LICENSE
chartify-5.0.1.dist-info/METADATA
chartify-5.0.1.dist-info/WHEEL
chartify-5.0.1.dist-info/top_level.txt
chartify-5.0.1.dist-info/RECORD
