Metadata-Version: 2.1
Name: chartify
Version: 5.0.1
Summary: Python library to make plotting simpler for data scientists
Home-page: https://github.com/spotify/chartify
Author: 
Author-email: chalpert@spotify.com
License: Apache 2
Keywords: chartify
Classifier: Development Status :: 4 - Beta
Classifier: Intended Audience :: Science/Research
Classifier: Natural Language :: English
Classifier: Programming Language :: Python :: 3.9
Classifier: Programming Language :: Python :: 3.10
Classifier: Programming Language :: Python :: 3.11
Classifier: License :: OSI Approved :: Apache Software License
Requires-Python: >=3.9,<4
License-File: LICENSE
License-File: AUTHORS.rst
Requires-Dist: pandas >=1.2.0
Requires-Dist: Pillow >=9.1.0
Requires-Dist: selenium >=4.0.0
Requires-Dist: bokeh >=3.4.2
Requires-Dist: scipy >=1.6.0
Requires-Dist: ipykernel >=6.0
Requires-Dist: ipython >=7.17.0
Requires-Dist: pyyaml >=6.0.0
Requires-Dist: Jinja2 >=3.1.0
Requires-Dist: jupyter-bokeh >=3.0.7
Requires-Dist: tornado >=6.3.2
